llama_index/llms/predibase/__init__.py
llama_index/llms/predibase/base.py
llama_index_llms_predibase-0.4.1.dist-info/METADATA
llama_index_llms_predibase-0.4.1.dist-info/WHEEL
llama_index_llms_predibase-0.4.1.dist-info/licenses/LICENSE
llama_index_llms_predibase-0.4.1.dist-info/RECORD
